windmilltrainingv1/__init__.py
windmilltrainingv1/client/__init__.py
windmilltrainingv1/client/training_api_dataset.py
windmilltrainingv1/client/training_api_job.py
windmilltrainingv1/client/training_api_pipeline.py
windmilltrainingv1/client/training_api_project.py
windmilltrainingv1/client/training_client.py
windmill_train-1.0.0.23.dist-info/METADATA
windmill_train-1.0.0.23.dist-info/WHEEL
windmill_train-1.0.0.23.dist-info/top_level.txt
windmill_train-1.0.0.23.dist-info/RECORD
