Metadata-Version: 2.1
Name: windmill-train
Version: 1.0.0.23
Summary: sdk in python for windmill artifact
Home-page: https://console.cloud.baidu-int.com/devops/icode/repos/baidu/themis/windmill-train/blob/master/sdk/python/training_client.py
Author: yangtingyu01
Author-email: yangtingyu01@baidu.com
License: MIT
Classifier: Programming Language :: Python
Classifier: Programming Language :: Python :: 3
Classifier: Programming Language :: Python :: 3.7
Classifier: Programming Language :: Python :: 3.8
Classifier: Programming Language :: Python :: 3.9
Requires-Python: >=3.6
Requires-Dist: bce-python-sdk (==0.8.87)
Requires-Dist: multidict (==6.0.4)
Requires-Dist: bce-internal-sdk
